argo_workflow_tools/__init__.py
argo_workflow_tools/argo_client.py
argo_workflow_tools/argo_http_client.py
argo_workflow_tools/argo_options.py
argo_workflow_tools/artifact.py
argo_workflow_tools/dsl/__init__.py
argo_workflow_tools/dsl/building_mode_context.py
argo_workflow_tools/dsl/condition.py
argo_workflow_tools/dsl/dag_compiler.py
argo_workflow_tools/dsl/dag_task.py
argo_workflow_tools/dsl/dsl_decorators.py
argo_workflow_tools/dsl/expression.py
argo_workflow_tools/dsl/input_definition.py
argo_workflow_tools/dsl/node.py
argo_workflow_tools/dsl/node_properties/__init__.py
argo_workflow_tools/dsl/node_properties/dag_node_properties.py
argo_workflow_tools/dsl/node_properties/task_node_properties.py
argo_workflow_tools/dsl/parameter_builders/__init__.py
argo_workflow_tools/dsl/parameter_builders/default_parameter_builder.py
argo_workflow_tools/dsl/parameter_builders/multiple_output_parameter_builder.py
argo_workflow_tools/dsl/parameter_builders/parameter_builder.py
argo_workflow_tools/dsl/utils/__init__.py
argo_workflow_tools/dsl/utils/path_builder.py
argo_workflow_tools/dsl/utils/utils.py
argo_workflow_tools/dsl/workflow.py
argo_workflow_tools/dsl/workflow_compiler.py
argo_workflow_tools/dsl/workflow_template_collector.py
argo_workflow_tools/exceptions/__init__.py
argo_workflow_tools/exceptions/workflow_not_found_exception.py
argo_workflow_tools/merge_result.py
argo_workflow_tools/models/__init__.py
argo_workflow_tools/models/eventsource.py
argo_workflow_tools/models/io/__init__.py
argo_workflow_tools/models/io/argoproj/__init__.py
argo_workflow_tools/models/io/argoproj/events/__init__.py
argo_workflow_tools/models/io/argoproj/events/v1alpha1.py
argo_workflow_tools/models/io/argoproj/workflow/__init__.py
argo_workflow_tools/models/io/argoproj/workflow/v1alpha1.py
argo_workflow_tools/models/io/k8s/__init__.py
argo_workflow_tools/models/io/k8s/api/__init__.py
argo_workflow_tools/models/io/k8s/api/core/__init__.py
argo_workflow_tools/models/io/k8s/api/core/v1.py
argo_workflow_tools-0.9.55.dist-info/LICENSE
argo_workflow_tools-0.9.55.dist-info/METADATA
argo_workflow_tools-0.9.55.dist-info/WHEEL
argo_workflow_tools-0.9.55.dist-info/RECORD
