Metadata-Version: 2.1
Name: argo-workflow-tools
Version: 0.9.55
Summary: A suite of tools to ease ML pipeline development with Argo Workflows
Home-page: https://github.com/DiagnosticRobotics/argo-workflow-tools
License: Apache 2.0
Author: Diagnostic Robotics
Requires-Python: >=3.7,<3.11
Classifier: License :: Other/Proprietary License
Classifier: Programming Language :: Python :: 3
Classifier: Programming Language :: Python :: 3.7
Classifier: Programming Language :: Python :: 3.8
Classifier: Programming Language :: Python :: 3.9
Classifier: Programming Language :: Python :: 3.10
Requires-Dist: PyYAML (>=5.4)
Requires-Dist: certifi (<=2022.12.7)
Requires-Dist: contextvars (>=2.4,<3.0)
Requires-Dist: pydantic (>=1.7.4,<2.0.0)
Requires-Dist: requests (>=2.26.0,<3.0.0)
Requires-Dist: shortuuid (>=1.0.8,<2.0.0)
Requires-Dist: urllib3 (<2.0.0)
Project-URL: Repository, https://github.com/DiagnosticRobotics/argo-workflow-tools
